{"inkVersion":21,"root":[["\n",{"->":"main"},["done",{"#f":5,"#n":"g-0"}],null],"done",{"main":[["^Selamat pagi ayah  ","#","^speaker:Putra ","/#","#","^portrait:Putra ","/#","#","^layout:left","/#","\n","^Selamat pagi, bagaimana belajarmu? ","#","^speaker:Ayah ","/#","#","^portrait:Ayah ","/#","#","^layout:right","/#","\n",["^Aman ayah, aku yakin masih bisa berkembang  ","#","^speaker:Putra ","/#","#","^portrait:Putra ","/#","#","^layout:left","/#","\n","^Hoho, itu baru semangat, jangan lupa jaga dirimu dari godaan dan hal hal negatif ","#","^speaker:Ayah ","/#","#","^portrait:Ayah ","/#","#","^layout:right","/#","\n","^Hal yang instan tidak selalu baik, apalagi dalam proses belajar","\n","ev","str","^Iya yah aku setuju”","/str","/ev",{"*":".^.c-0","flg":4},"ev","str","^Semakin cepat semakin baik yah..","/str","/ev",{"*":".^.c-1","flg":4},{"c-0":["#","^nilai=4 ","/#","#","^portrait:Putra ","/#","#","^layout:left","/#","\n","^Hal yang instan memang menggiurkan, tapi seringkali tidak bertahan lama ya yah","\n","^Betul itu, karena kalau kamu tergiur dengan yang instan","#","^speaker:Ayah ","/#","#","^portrait:Ayah ","/#","#","^layout:right","/#","\n","^Maka sebenarnya kamu melakukan pelanggaran poin bela negara","\n",{"->":"main.0.g-1"},{"#f":5}],"c-1":["#","^nilai=2 ","/#","#","^portrait:Putra ","/#","#","^layout:left","/#","\n","^Semakin cepat aku lulus kan semakin cepat aku berbakti kepada negara yah","\n","^Itu pemikiran yang kurang tepat, memang benar semakin cepat lulus, semakin kamu cepat berbakti kepada negara","#","^speaker:Ayah ","/#","#","^portrait:Ayah ","/#","#","^layout:right","/#","\n","^Tapi perlu kamu ingat dalam prosesnya, jika menggunakan kecurangan maka tidak akan berkah","\n","^Dan itu juga bertentangan dengan poin bela negara","\n",{"->":"main.0.g-1"},{"#f":5}],"#f":5,"#n":"g-0"}],{"g-1":["^oh iya yah? itu melanggar poin bela negara?","#","^portrait:Putra ","/#","#","^layout:left","/#","\n","^Jelas, di poin bela negara kamu harus memiliki kemampuan awal bela negara","#","^speaker:Ayah ","/#","#","^portrait:Ayah ","/#","#","^layout:right","/#","\n","^yaitu secara psikis (mental) memiliki sifat disiplin, ulet, mentaati segala peraturan perundang-undangan yang berlaku","\n","^Nah dengan melakukan kecurangan artinya kamu tidak disiplin dan tidak mengikuti peraturan.","\n","^Terima kasih untuk masukannya Ayah  ","#","^speaker:Putra ","/#","#","^portrait:Putra ","/#","#","^layout:left","/#","\n","^Heh, sekarang pergilah, lakukan apa yang kamu perlukan ","#","^speaker:Ayah ","/#","#","^portrait:Ayah ","/#","#","^layout:right","/#","\n","^SHAP  ","#","^speaker:Putra ","/#","#","^portrait:Putra ","/#","#","^layout:left","/#","\n","end",{"#f":5}]}],{"#f":1}],"global decl":["ev","str","^","/str",{"VAR=":"pokemon_name"},0,{"VAR=":"dialogValue"},"/ev","end",null],"#f":1}],"listDefs":{}}