{"inkVersion":21,"root":[["\n",{"->":"main"},["done",{"#f":5,"#n":"g-0"}],null],"done",{"main":["^Bagaimana ujiannya? ","#","^speaker:Mentor ","/#","#","^portrait:Mentor ","/#","#","^layout:right","/#","\n","^Kurasa, tidak sebaik yang kuharapkan, mentor ","#","^speaker:Putra ","/#","#","^portrait:Putra ","/#","#","^layout:left","/#","\n","^Jangan kecewa, yang penting sudah berusaha ","#","^speaker:Mentor ","/#","#","^portrait:Mentor ","/#","#","^layout:right","/#","\n","end",{"#f":1}],"global decl":["ev","str","^","/str",{"VAR=":"pokemon_name"},"/ev","end",null],"#f":1}],"listDefs":{}}