{"inkVersion":21,"root":[["\n",{"->":"main"},["done",{"#f":5,"#n":"g-0"}],null],"done",{"main":["^Selamat pagi~! ","#","^speaker:Mentor ","/#","#","^portrait:Mentor ","/#","#","^layout:right","/#","\n","^Selamat pagi mentor!! ","#","^speaker:Putra ","/#","#","^portrait:Putra ","/#","#","^layout:left","/#","\n","^Kamu tidak lupa kalau hari ini ada ujian, kan? ","#","^speaker:Mentor ","/#","#","^portrait:Mentor ","/#","#","^layout:right","/#","\n","^Tentu saja tidak, aku sangat bersemangat!!! ","#","^speaker:Putra ","/#","#","^portrait:Putra ","/#","#","^layout:left","/#","\n","^Karena ini hari penting, jangan lupa beritahu orang tuamu! ","#","^speaker:Mentor ","/#","#","^portrait:Mentor ","/#","#","^layout:right","/#","\n","^Jangan sampai kamu melupakan hal - hal sederhana seperti ini ya","\n","^Restu mereka adalah jalan bagimu~!","\n","^Baiklah, mentor juga doakan aku ya~ ","#","^speaker:Putra ","/#","#","^portrait:Putra ","/#","#","^layout:left","/#","\n","^.... ","#","^speaker:Mentor ","/#","#","^portrait:Mentor ","/#","#","^layout:right","/#","\n","^Tentu saja, jangan lupa kalau aku adalah pembimbingmu","\n","end",{"#f":1}],"global decl":["ev","str","^","/str",{"VAR=":"pokemon_name"},"/ev","end",null],"#f":1}],"listDefs":{}}